bismillah_on_py/__init__.py
bismillah_on_py/bismillah.py
bismillah_on_py-1.0.1.dist-info/LICENSE
bismillah_on_py-1.0.1.dist-info/METADATA
bismillah_on_py-1.0.1.dist-info/WHEEL
bismillah_on_py-1.0.1.dist-info/RECORD
